sphinxcontrib_jsdemo-0.1.4-py2.7-nspkg.pth
sphinxcontrib/jsdemo.js
sphinxcontrib/jsdemo.py
sphinxcontrib/jsdemo.css
sphinxcontrib_jsdemo-0.1.4.dist-info/RECORD
sphinxcontrib_jsdemo-0.1.4.dist-info/DESCRIPTION.rst
sphinxcontrib_jsdemo-0.1.4.dist-info/metadata.json
sphinxcontrib_jsdemo-0.1.4.dist-info/METADATA
sphinxcontrib_jsdemo-0.1.4.dist-info/top_level.txt
sphinxcontrib_jsdemo-0.1.4.dist-info/namespace_packages.txt
sphinxcontrib_jsdemo-0.1.4.dist-info/WHEEL
